semantic_pdf_search/__init__.py
semantic_pdf_search/gui.py
semantic_pdf_search/main.py
semantic_pdf_search-0.8.4.dist-info/licenses/LICENSE
semantic_pdf_search-0.8.4.dist-info/METADATA
semantic_pdf_search-0.8.4.dist-info/WHEEL
semantic_pdf_search-0.8.4.dist-info/entry_points.txt
semantic_pdf_search-0.8.4.dist-info/top_level.txt
semantic_pdf_search-0.8.4.dist-info/RECORD
