Metadata-Version: 2.4
Name: semantic-pdf-search
Version: 0.8.4
Summary: Search PDFs semantically
Author: notjonathanlouis
Project-URL: Homepage, https://github.com/notjonathanlouis/semantic-pdf-search
Requires-Python: >=3.6
License-File: LICENSE
Requires-Dist: customtkinter
Requires-Dist: pymupdf
Requires-Dist: torch
Requires-Dist: sentence-transformers
Dynamic: license-file
